pylabianca/__init__.py
pylabianca/_numba.py
pylabianca/decoding.py
pylabianca/io.py
pylabianca/localize.py
pylabianca/neuralynx_io.py
pylabianca/postproc.py
pylabianca/selectivity.py
pylabianca/spike_distance.py
pylabianca/spike_rate.py
pylabianca/spikes.py
pylabianca/stats.py
pylabianca/testing.py
pylabianca/utils.py
pylabianca/viz.py
pylabianca/scripts/anonymize_dicom_files.py
pylabianca/scripts/manipulate_fieldtrip_events.py
pylabianca/scripts/mass_convert_dicom_to_nii.py
pylabianca/scripts/spike_postproc_choose_ref.py
pylabianca/scripts/spike_postproc_choose_ref_mm.py
pylabianca/scripts/spike_postproc_correct_mixed_alignment.py
pylabianca/scripts/test_region_changes.py
pylabianca/test/test_io.py
pylabianca/test/test_numba.py
pylabianca/test/test_selectivity.py
pylabianca/test/test_spike_distance.py
pylabianca/test/test_spike_rate.py
pylabianca/test/test_spikes.py
pylabianca/test/test_stats.py
pylabianca/test/test_utils.py
pylabianca-0.3.0.dist-info/LICENSE
pylabianca-0.3.0.dist-info/METADATA
pylabianca-0.3.0.dist-info/WHEEL
pylabianca-0.3.0.dist-info/top_level.txt
pylabianca-0.3.0.dist-info/RECORD
