Metadata-Version: 2.1
Name: pylabianca
Version: 0.3.0
Summary: Package for analysis of single-neuron spike data.
Maintainer-email: Mikołaj Magnuski <mmagnuski@swps.edu.pl>
License: MIT
Project-URL: Homepage, https://github.com/labianca/pylabianca
Keywords: neuroscience,brain
Classifier: Intended Audience :: Science/Research
Classifier: Intended Audience :: Developers
Classifier: License :: OSI Approved
Classifier: Programming Language :: Python
Classifier: Topic :: Software Development
Classifier: Topic :: Scientific/Engineering
Classifier: Operating System :: Microsoft :: Windows
Classifier: Operating System :: POSIX
Classifier: Operating System :: Unix
Classifier: Operating System :: MacOS
Classifier: Programming Language :: Python :: 3
Requires-Python: >=3.8
License-File: LICENSE
Requires-Dist: numpy>=1.15.4
Requires-Dist: scipy>=1.7.1
Requires-Dist: matplotlib>=3.5.0
Requires-Dist: pandas
Requires-Dist: scikit-learn
Requires-Dist: borsar
Requires-Dist: h5io
Requires-Dist: h5py
Requires-Dist: xlrd
Requires-Dist: xarray
Provides-Extra: all
Requires-Dist: mne>=1.0.0; extra == "all"
Requires-Dist: neo; extra == "all"
Requires-Dist: joblib; extra == "all"
Requires-Dist: numba; extra == "all"
Requires-Dist: tqdm; extra == "all"
Requires-Dist: pooch; extra == "all"
